pxdlib/__init__.py
pxdlib/enums.py
pxdlib/errors.py
pxdlib/helpers.py
pxdlib/layer.py
pxdlib/pxdfile.py
pxdlib/structure.py
pxdlib/styles.py
pxdlib-0.0.4.dist-info/LICENSE
pxdlib-0.0.4.dist-info/METADATA
pxdlib-0.0.4.dist-info/WHEEL
pxdlib-0.0.4.dist-info/top_level.txt
pxdlib-0.0.4.dist-info/RECORD
