Metadata-Version: 2.1
Name: pxdlib
Version: 0.0.4
Summary: Pixelmator Pro file (.pxd) library
Home-page: https://github.com/yunruse/pxdlib
Author: Mia yun Ruse
Author-email: mia@yunru.se
License: UNKNOWN
Keywords: Pixelmator pxd file image raster vector
Platform: UNKNOWN
Classifier: Development Status :: 3 - Alpha
Classifier: License :: OSI Approved :: MIT License
Classifier: Operating System :: OS Independent
Classifier: Programming Language :: Python :: 3
Classifier: Topic :: Multimedia :: Graphics :: Editors
Requires-Python: >=3.6
